{"about_join.md":"c9ab292d","about_us.md":"a2b47ab9","api_canvas.md":"c51110b9","api_core.md":"89ef3915","api_layout.md":"c0628b76","api_pen.md":"42378eaa","api_point.md":"646c4fdf","api_rect.md":"34b4006b","api_utils.md":"8eec11b6","awesome_home.md":"d84299f4","community_gitee.md":"7c01db59","community_github.md":"fb738bf5","community_wechat.md":"8e3584e1","home.md":"abb4202e","index.md":"55488450","instruction_home.md":"6b1c4da9","resources_install.md":"226d4d70","tutorial_animate.md":"e28fe869","tutorial_architecture.md":"7b9b2375","tutorial_attention.md":"7c989e83","tutorial_auto-anchor.md":"6d7fcde8","tutorial_changelog.md":"ba29b62d","tutorial_charts.md":"fb13d589","tutorial_commercial-api.md":"04b967ba","tutorial_commercial-trial.md":"dc85520b","tutorial_commercial.md":"34298402","tutorial_data.md":"7aa777c5","tutorial_drag.md":"ed6571ed","tutorial_events.md":"3ae4de6d","tutorial_faq.md":"421470fc","tutorial_forms.md":"e4b99dd5","tutorial_grid.md":"d7566fdc","tutorial_icons.md":"f5005c39","tutorial_introduction.md":"ec3420be","tutorial_keyboards.md":"3962ed78","tutorial_layout.md":"fc6762f9","tutorial_lifecycle.md":"e8b3987b","tutorial_line-ai.md":"e09d816d","tutorial_magnifier.md":"da4f41d7","tutorial_make-component.md":"764abc39","tutorial_map.md":"2b0f6b5e","tutorial_pen-draw.md":"fc4c6271","tutorial_pen.md":"e9cd4cda","tutorial_pencil.md":"ab474593","tutorial_pens.md":"c9f68433","tutorial_progress.md":"7dda598b","tutorial_right-menu.md":"e8895a35","tutorial_rule.md":"209464e9","tutorial_service-data.md":"b6c58f52","tutorial_start.md":"358bb496","tutorial_svg-to-combine.md":"843de585","tutorial_table.md":"b7bf0614","tutorial_topology.md":"74cac6a4","tutorial_tuxingku.md":"3f508e57","tutorial_updatelog.md":"00215a81","tutorial_video.md":"23dfef85","videos_home.md":"d8304a79"}
