{"about_join.md":"5b1933f5","about_us.md":"3ab9f8ac","api_canvas.md":"c964f438","api_core.md":"60231742","api_layout.md":"07aec66d","api_pen.md":"b8958446","api_point.md":"3034124f","api_rect.md":"ddb43fc3","api_utils.md":"a084321d","awesome_home.md":"5301b24b","community_gitee.md":"3b2092d3","community_github.md":"d5057803","community_wechat.md":"e84c9e14","home.md":"2cc1d6f0","index.md":"39d5c863","instruction_home.md":"a99d94f5","resources_install.md":"d692ed6a","tutorial_animate.md":"c9d7f51e","tutorial_architecture.md":"f83f5156","tutorial_attention.md":"b2ec609f","tutorial_auto-anchor.md":"c1f345cd","tutorial_changelog.md":"09e6553f","tutorial_charts.md":"ba5871e1","tutorial_commercial-api.md":"1ef8f970","tutorial_commercial-trial.md":"b7dfc53e","tutorial_commercial.md":"50823085","tutorial_data.md":"60ef3ceb","tutorial_drag.md":"5d9dcc9e","tutorial_events.md":"d9a2b804","tutorial_faq.md":"b3c183ce","tutorial_forms.md":"53616489","tutorial_grid.md":"2df987c9","tutorial_icons.md":"8b212c8a","tutorial_introduction.md":"4a64aa41","tutorial_keyboards.md":"a60e439e","tutorial_layout.md":"675354b2","tutorial_lifecycle.md":"c0946698","tutorial_line-ai.md":"eb83241f","tutorial_magnifier.md":"3e7e4835","tutorial_make-component.md":"6203c5ca","tutorial_map.md":"8eab1a39","tutorial_meta2d.md":"6a62c475","tutorial_pen-draw.md":"2aaf4956","tutorial_pen.md":"e96aeaa5","tutorial_pencil.md":"8ef3727f","tutorial_pens.md":"78a78984","tutorial_progress.md":"c87bc286","tutorial_right-menu.md":"b7ba67c4","tutorial_rule.md":"c29f76b4","tutorial_service-data.md":"416c7686","tutorial_start.md":"e19b1955","tutorial_svg-to-combine.md":"bd65a3bb","tutorial_table.md":"59c27386","tutorial_tuxingku.md":"6c804206","tutorial_updatelog.md":"f9c66f57","tutorial_video.md":"ce846283","videos_home.md":"d1754d75"}
